dty/__init__.py
dty/main.py
dty-0.1.1.dist-info/LICENSE
dty-0.1.1.dist-info/METADATA
dty-0.1.1.dist-info/WHEEL
dty-0.1.1.dist-info/entry_points.txt
dty-0.1.1.dist-info/top_level.txt
dty-0.1.1.dist-info/RECORD
