Metadata-Version: 2.1
Name: dty
Version: 0.1.1
Summary: A tool to convert directory contents to YAML.
Home-page: https://github.com/adriangalilea/dty
Author: Adrian Galilea Delgado
Author-email: adriangalilea@gmail.com
Classifier: Programming Language :: Python :: 3
Classifier: License :: OSI Approved :: MIT License
Classifier: Operating System :: OS Independent
License-File: LICENSE
Requires-Dist: rich
Requires-Dist: pyperclip
Requires-Dist: pyyaml
